qctrl/__init__.py
qctrl/builders/__init__.py
qctrl/builders/async_result.py
qctrl/builders/client_builder.py
qctrl/builders/custom_environment.py
qctrl/builders/custom_handlers/__init__.py
qctrl/builders/custom_handlers/complex_array_entry_handler.py
qctrl/builders/custom_handlers/complex_array_handler.py
qctrl/builders/custom_handlers/complex_array_input_handler.py
qctrl/builders/custom_handlers/complex_number_handler.py
qctrl/builders/custom_handlers/complex_number_input_handler.py
qctrl/builders/custom_handlers/scalars.py
qctrl/builders/doc.py
qctrl/builders/functions.py
qctrl/builders/graphql_utils/__init__.py
qctrl/builders/graphql_utils/base_type_registry.py
qctrl/builders/graphql_utils/environment.py
qctrl/builders/graphql_utils/handlers/__init__.py
qctrl/builders/graphql_utils/handlers/base.py
qctrl/builders/graphql_utils/handlers/enum_handler.py
qctrl/builders/graphql_utils/handlers/input_object_handler.py
qctrl/builders/graphql_utils/handlers/list_handler.py
qctrl/builders/graphql_utils/handlers/mixins.py
qctrl/builders/graphql_utils/handlers/non_null_handler.py
qctrl/builders/graphql_utils/handlers/object_handler.py
qctrl/builders/graphql_utils/handlers/scalar_handler.py
qctrl/builders/graphql_utils/handlers/union_handler.py
qctrl/builders/http_transport.py
qctrl/builders/namespaces.py
qctrl/builders/result_mixin.py
qctrl/builders/type_registry.py
qctrl/builders/utils.py
qctrl/builders/verbosity.py
qctrl/builders/wait.py
qctrl/cite.py
qctrl/constants.py
qctrl/dynamic.py
qctrl/graphs.py
qctrl/mutations/__init__.py
qctrl/mutations/request_machines.py
qctrl/mutations/update_action.py
qctrl/nodes/__init__.py
qctrl/nodes/arithmetic_binary.py
qctrl/nodes/arithmetic_unary.py
qctrl/nodes/attribute.py
qctrl/nodes/deprecation.py
qctrl/nodes/differentiation.py
qctrl/nodes/documentation.py
qctrl/nodes/filter_function.py
qctrl/nodes/fock_space.py
qctrl/nodes/infidelity.py
qctrl/nodes/ms.py
qctrl/nodes/node_data.py
qctrl/nodes/optimization.py
qctrl/nodes/oqs.py
qctrl-24.2.0.dist-info/LICENSE
qctrl-24.2.0.dist-info/METADATA
qctrl-24.2.0.dist-info/WHEEL
qctrl-24.2.0.dist-info/entry_points.txt
qctrl-24.2.0.dist-info/RECORD
