Metadata-Version: 2.1
Name: qctrl
Version: 24.2.0
Summary: Q-CTRL Python
Home-page: https://q-ctrl.com
License: https://q-ctrl.com/terms
Keywords: black opal,boulder opal,fire opal,nisq,open controls,q control,q ctrl,q-control,q-ctrl,qcontrol,qctrl,quantum,quantum algorithms,quantum circuits,quantum coding,quantum coding software,quantum computing,quantum control,quantum control software,quantum control theory,quantum engineering,quantum error correction,quantum firmware,quantum fundamentals,quantum sensing,qubit,qudit
Author: Q-CTRL
Author-email: support@q-ctrl.com
Maintainer: Q-CTRL
Maintainer-email: support@q-ctrl.com
Requires-Python: >=3.8,<3.12
Classifier: Development Status :: 5 - Production/Stable
Classifier: Environment :: Console
Classifier: Intended Audience :: Developers
Classifier: Intended Audience :: Education
Classifier: Intended Audience :: Science/Research
Classifier: License :: Other/Proprietary License
Classifier: Natural Language :: English
Classifier: Operating System :: OS Independent
Classifier: Programming Language :: Python :: 3
Classifier: Programming Language :: Python :: 3.8
Classifier: Programming Language :: Python :: 3.9
Classifier: Programming Language :: Python :: 3.10
Classifier: Programming Language :: Python :: 3.11
Classifier: Topic :: Internet :: WWW/HTTP
Classifier: Topic :: Scientific/Engineering :: Physics
Classifier: Topic :: Scientific/Engineering :: Visualization
Classifier: Topic :: Software Development :: Embedded Systems
Classifier: Topic :: System :: Distributed Computing
Requires-Dist: attrs (>=23.1.0,<24.0.0)
Requires-Dist: boulder-opal-toolkits (==2.0.0-beta.9)
Requires-Dist: cached-property (>=1.5.1,<2.0.0)
Requires-Dist: click (>=8.0,<9.0)
Requires-Dist: commonmark (>=0.9.1,<0.10.0)
Requires-Dist: gql[requests] (>=3.4.0,<4.0.0)
Requires-Dist: importlib-metadata (>=6.8.0,<7.0.0)
Requires-Dist: inflection (>=0.5.1,<0.6.0)
Requires-Dist: numpy (>=1.23.5,<2.0.0)
Requires-Dist: packaging (>=23.1,<24.0)
Requires-Dist: pyjwt (>=2.4.0,<3.0.0)
Requires-Dist: python-dateutil (>=2.8.1,<3.0.0)
Requires-Dist: python-forge (>=18.6.0,<19.0.0)
Requires-Dist: pytz (>=2023.3,<2024.0)
Requires-Dist: qctrl-commons (>=21.2.2,<22.0.0)
Requires-Dist: qctrl-visualizer (>=6.2.0,<7.0.0)
Requires-Dist: requests (>=2.31.0,<3.0.0)
Requires-Dist: requests-oauthlib (>=1.3.0,<2.0.0)
Requires-Dist: rich (>=13.5.2,<14.0.0)
Requires-Dist: tenacity (>=8.1.0,<9.0.0)
Requires-Dist: tomli (>=2.0.1,<3.0.0)
Requires-Dist: tqdm (>=4.63.0)
Requires-Dist: typing-utils (>=0.1.0,<0.2.0)
Requires-Dist: urllib3 (>=1.26.8,<1.27.0)
Project-URL: Documentation, https://docs.q-ctrl.com/references/qctrl/
Project-URL: Facebook, https://www.facebook.com/qctrl
Project-URL: GitHub, https://github.com/qctrl
Project-URL: LinkedIn, https://www.linkedin.com/company/q-ctrl/
Project-URL: Twitter, https://twitter.com/qctrlHQ
Project-URL: YouTube, https://www.youtube.com/qctrl
